anymodality/__init__.py
anymodality/llms/__init__.py
anymodality/llms/base.py
anymodality/llms/replicate.py
anymodality/llms/sagemaker.py
anymodality/tasks/__init__.py
anymodality/tasks/base.py
anymodality-0.1.0.dist-info/LICENSE
anymodality-0.1.0.dist-info/METADATA
anymodality-0.1.0.dist-info/WHEEL
anymodality-0.1.0.dist-info/RECORD
